README.md
setup.py
github_fluent_api/__init__.py
github_fluent_api/_base_client.py
github_fluent_api/_client.py
github_fluent_api/_compat.py
github_fluent_api/_constants.py
github_fluent_api/_exceptions.py
github_fluent_api/_files.py
github_fluent_api/_models.py
github_fluent_api/_qs.py
github_fluent_api/_resource.py
github_fluent_api/_response.py
github_fluent_api/_streaming.py
github_fluent_api/_types.py
github_fluent_api/_version.py
github_fluent_api/py.typed
github_fluent_api.egg-info/PKG-INFO
github_fluent_api.egg-info/SOURCES.txt
github_fluent_api.egg-info/dependency_links.txt
github_fluent_api.egg-info/requires.txt
github_fluent_api.egg-info/top_level.txt
github_fluent_api/_utils/__init__.py
github_fluent_api/_utils/_logs.py
github_fluent_api/_utils/_proxy.py
github_fluent_api/_utils/_reflection.py
github_fluent_api/_utils/_streams.py
github_fluent_api/_utils/_sync.py
github_fluent_api/_utils/_transform.py
github_fluent_api/_utils/_typing.py
github_fluent_api/_utils/_utils.py
github_fluent_api/resources/__init__.py
github_fluent_api/resources/advisories.py
github_fluent_api/resources/app_manifests.py
github_fluent_api/resources/assignments.py
github_fluent_api/resources/classrooms.py
github_fluent_api/resources/codes_of_conduct.py
github_fluent_api/resources/emojis.py
github_fluent_api/resources/events.py
github_fluent_api/resources/feeds.py
github_fluent_api/resources/installation.py
github_fluent_api/resources/issues.py
github_fluent_api/resources/licenses.py
github_fluent_api/resources/markdown.py
github_fluent_api/resources/meta.py
github_fluent_api/resources/networks.py
github_fluent_api/resources/octocat.py
github_fluent_api/resources/rate_limit.py
github_fluent_api/resources/repositories.py
github_fluent_api/resources/zen.py
github_fluent_api/resources/applications/__init__.py
github_fluent_api/resources/applications/applications.py
github_fluent_api/resources/applications/hook/__init__.py
github_fluent_api/resources/applications/hook/config.py
github_fluent_api/resources/applications/hook/deliveries.py
github_fluent_api/resources/applications/hook/hook.py
github_fluent_api/resources/applications/installations/__init__.py
